{
  "project_info": {
    "project_number": "760082000923",
    "project_id": "snevva-aef81",
    "storage_bucket": "snevva-aef81.firebasestorage.app"
  },
  "client": [
    {
      "client_info": {
        "mobilesdk_app_id": "1:760082000923:android:9eaf15914293799ba3dcbe",
        "android_client_info": {
          "package_name": "com.coretegra.snevva"
        }
      },
      "oauth_client": [],
      "api_key": [
        {
          "current_key": "AIzaSyCUAz5H5yHgpZl8DHnEScp_O3weEXndQIE"
        }
      ],
      "services": {
        "appinvite_service": {
          "other_platform_oauth_client": [
            {
              "client_id": "760082000923-v6lm2bqqroimspg8f1am01ntbio5mbn0.apps.googleusercontent.com",
              "client_type": 3
            }
          ]
        }
      }
    }
  ],
  "configuration_version": "1"
}